fastapi_swagger/__init__.py
fastapi_swagger/main.py
fastapi_swagger/resources/__init__.py
fastapi_swagger/resources/favicon-32x32.png
fastapi_swagger/resources/swagger-ui-bundle.js
fastapi_swagger/resources/swagger-ui.css
fastapi_swagger-0.4.41.dist-info/METADATA
fastapi_swagger-0.4.41.dist-info/WHEEL
fastapi_swagger-0.4.41.dist-info/licenses/LICENSE
fastapi_swagger-0.4.41.dist-info/RECORD
