Metadata-Version: 2.4
Name: fastapi-swagger
Version: 0.4.41
Summary: This plugin updates the FastAPI app to host latest Swagger UI distribution.
Project-URL: Homepage, https://github.com/dantetemplar/fastapi-swagger
Project-URL: Repository, https://github.com/dantetemplar/fastapi-swagger
Author-email: Ruslan Bel'kov <ruslan.belckov@yandex.ru>
License-Expression: MIT
License-File: LICENSE
Classifier: Development Status :: 5 - Production/Stable
Classifier: Intended Audience :: Developers
Classifier: License :: OSI Approved :: MIT License
Classifier: Operating System :: OS Independent
Classifier: Programming Language :: Python :: 3
Requires-Python: ~=3.10
Requires-Dist: fastapi>=0.100
